{
  "project_info": {
    "project_number": "881333074318",
    "project_id": "voguevoyage27",
    "storage_bucket": "voguevoyage27.appspot.com"
  },
  "client": [
    {
      "client_info": {
        "mobilesdk_app_id": "1:881333074318:android:107b4e1dba77b12a2cccdf",
        "android_client_info": {
          "package_name": "com.example.voguevoyage"
        }
      },
      "oauth_client": [
        {
          "client_id": "881333074318-pm56j1rbbel92kokn50b1sjdsm2dd39u.apps.googleusercontent.com",
          "client_type": 3
        }
      ],
      "api_key": [
        {
          "current_key": "AIzaSyANDfm7GoD4winvi5_PKV2sRiXf4t3cCKc"
        }
      ],
      "services": {
        "appinvite_service": {
          "other_platform_oauth_client": [
            {
              "client_id": "881333074318-pm56j1rbbel92kokn50b1sjdsm2dd39u.apps.googleusercontent.com",
              "client_type": 3
            },
            {
              "client_id": "881333074318-pfqqn10uq5pvusa7g1tuseo80i8m8p20.apps.googleusercontent.com",
              "client_type": 2,
              "ios_info": {
                "bundle_id": "com.example.clothing.RunnerTests"
              }
            }
          ]
        }
      }
    }
  ],
  "configuration_version": "1"
}